{
    "Monday": [
        [
            {
                "subject": "Мат. анализ",
                "sub_type": "лк",
                "professor": "Игонина Т.Р.",
                "room": "Д",
                "link": "-"
            },
            {
                "subject": "Мат. анализ",
                "sub_type": "лк",
                "professor": "Игонина Т.Р.",
                "room": "Д",
                "link": "-"
            }
        ],
        [
            {
                "subject": "Мат. анализ",
                "sub_type": "пр",
                "professor": "Кузнецова Е.Ю.",
                "room": "Д",
                "link": "-"
            },
            {
                "subject": "Мат. анализ",
                "sub_type": "пр",
                "professor": "Кузнецова Е.Ю.",
                "room": "Д",
                "link": "-"
            }
        ],
        [
            {
                "subject": "Лин. алгебра и АГ",
                "sub_type": "пр",
                "professor": "Кузнецова Е.Ю.",
                "room": "Д",
                "link": "-"
            },
            {
                "subject": "Лин. алгебра и АГ",
                "sub_type": "пр",
                "professor": "Кузнецова Е.Ю.",
                "room": "Д",
                "link": "-"
            }
        ],
        [
            {
                "subject": "Физ.культура и спорт",
                "sub_type": "-",
                "professor": "-",
                "room": "Д",
                "link": "-"
            },
            {
                "subject": "Физ.культура и спорт",
                "sub_type": "-",
                "professor": "-",
                "room": "Д",
                "link": "-"
            }
        ],
        [
            {
                "subject": "Структуры и АОД",
                "sub_type": "лк",
                "professor": "Скворцова Л.А.",
                "room": "Д",
                "link": "-"
            },
            {
                "subject": "ОО программирование 12 н. Структуры и АОД",
                "sub_type": "лк\nпр",
                "professor": "Путуридзе З.Ш.\nСкворцова Л.А.",
                "room": "Д",
                "link": "-"
            }
        ],
        [
            {
                "subject": "-",
                "sub_type": "-",
                "professor": "-",
                "room": "-",
                "link": "-"
            },
            {
                "subject": "ОО программирование 12 н. Правоведение",
                "sub_type": "лк\nпр",
                "professor": "Путуридзе З.Ш.\nМилкина Е.В.",
                "room": "Д",
                "link": "-"
            }
        ]
    ],
    "Tuesday": [
        [
            {
                "subject": "Структуры и АОД",
                "sub_type": "лк",
                "professor": "Скворцова Л.А.",
                "room": "Д",
                "link": "-"
            },
            {
                "subject": "Правоведение 4,12,16 н. Правоведение",
                "sub_type": "лк\nпр",
                "professor": "Милкина Е.В.\nМилкина Е.В.",
                "room": "Д",
                "link": "-"
            }
        ],
        [
            {
                "subject": "Структуры и АОД",
                "sub_type": "пр",
                "professor": "Скворцова Л.А.",
                "room": "Д",
                "link": "-"
            },
            {
                "subject": "Структуры и АОД",
                "sub_type": "пр",
                "professor": "Скворцова Л.А.",
                "room": "Д",
                "link": "-"
            }
        ],
        [
            {
                "subject": "ОО программирование",
                "sub_type": "пр",
                "professor": "Игнатьев Ф.А.",
                "room": "Д",
                "link": "-"
            },
            {
                "subject": "-",
                "sub_type": "-",
                "professor": "-",
                "room": "-",
                "link": "-"
            }
        ],
        [
            {
                "subject": "ОО программирование",
                "sub_type": "пр",
                "professor": "Игнатьев Ф.А.",
                "room": "Д",
                "link": "-"
            },
            {
                "subject": "-",
                "sub_type": "-",
                "professor": "-",
                "room": "-",
                "link": "-"
            }
        ],
        [
            {
                "subject": "Мат. логика и ТА",
                "sub_type": "пр",
                "professor": "пм",
                "room": "Д",
                "link": "-"
            },
            {
                "subject": "-",
                "sub_type": "-",
                "professor": "-",
                "room": "-",
                "link": "-"
            }
        ],
        [
            {
                "subject": "Структуры и АОД",
                "sub_type": "пр",
                "professor": "Скворцова Л.А.",
                "room": "Д",
                "link": "-"
            },
            {
                "subject": "Мат. логика и ТА",
                "sub_type": "лк",
                "professor": "Воронцов А.А.",
                "room": "Д",
                "link": "-"
            }
        ]
    ],
    "Wednesday": [
        [
            {
                "subject": "Ознакомительная практика",
                "sub_type": "-",
                "professor": "-",
                "room": "Д",
                "link": "-"
            },
            {
                "subject": "Ознакомительная практика",
                "sub_type": "-",
                "professor": "-",
                "room": "Д",
                "link": "-"
            }
        ],
        [
            {
                "subject": "Ознакомительная практика",
                "sub_type": "-",
                "professor": "-",
                "room": "Д",
                "link": "-"
            },
            {
                "subject": "Ознакомительная практика",
                "sub_type": "-",
                "professor": "-",
                "room": "Д",
                "link": "-"
            }
        ],
        [
            {
                "subject": "Ознакомительная практика",
                "sub_type": "-",
                "professor": "-",
                "room": "Д",
                "link": "-"
            },
            {
                "subject": "Ознакомительная практика",
                "sub_type": "-",
                "professor": "-",
                "room": "Д",
                "link": "-"
            }
        ],
        [
            {
                "subject": "Ознакомительная практика",
                "sub_type": "-",
                "professor": "-",
                "room": "Д",
                "link": "-"
            },
            {
                "subject": "Ознакомительная практика",
                "sub_type": "-",
                "professor": "-",
                "room": "Д",
                "link": "-"
            }
        ],
        [
            {
                "subject": "-",
                "sub_type": "-",
                "professor": "-",
                "room": "-",
                "link": "-"
            },
            {
                "subject": "-",
                "sub_type": "-",
                "professor": "-",
                "room": "-",
                "link": "-"
            }
        ],
        [
            {
                "subject": "-",
                "sub_type": "-",
                "professor": "-",
                "room": "-",
                "link": "-"
            },
            {
                "subject": "-",
                "sub_type": "-",
                "professor": "-",
                "room": "-",
                "link": "-"
            }
        ]
    ],
    "Thursday": [
        [
            {
                "subject": "Физика",
                "sub_type": "пр",
                "professor": "Логачев И.И.",
                "room": "Д",
                "link": "https://join.skype.com/i3l3usgN2WhD"
            },
            {
                "subject": "Физика",
                "sub_type": "пр",
                "professor": "Логачев И.И.",
                "room": "Д",
                "link": "-"
            }
        ],
        [
            {
                "subject": "Лин. алгебра и АГ",
                "sub_type": "лк",
                "professor": "Берков Н.А.",
                "room": "Д",
                "link": "https://events.webinar.ru/21586908/4632516"
            },
            {
                "subject": "Лин. алгебра и АГ",
                "sub_type": "лк",
                "professor": "Берков Н.А.",
                "room": "Д",
                "link": "-"
            }
        ],
        [
            {
                "subject": "Ин. язык (фр.)",
                "sub_type": "пр",
                "professor": "Иванова Е.А.",
                "room": "Д",
                "link": "-"
            },
            {
                "subject": "Физика",
                "sub_type": "лаб",
                "professor": "-",
                "room": "Д",
                "link": "-"
            }
        ],
        [
            {
                "subject": "Ин. язык Ин. язык (нем.)",
                "sub_type": "пр",
                "professor": "Прокопчук А.Р.\nНовоселова Е.В.",
                "room": "Д",
                "link": "https://us02web.zoom.us/j/2478596442?pwd=WWZwbU9nNlFHYm52cjl0SDNQM01OZz09 (Прокопчук), https://us02web.zoom.us/j/85601415261?pwd=NC91Y2pvcTA1TS9GNVdVcmVMc3pWZz09 (Новоселова)"
            },
            {
                "subject": "Ин. язык (нем.)",
                "sub_type": "пр",
                "professor": "Новоселова Е.В.",
                "room": "Д",
                "link": "-"
            }
        ],
        [
            {
                "subject": "Ин. язык",
                "sub_type": "пр",
                "professor": "Прокопчук А.Р.",
                "room": "Д",
                "link": "-"
            },
            {
                "subject": "Мат. анализ",
                "sub_type": "пр",
                "professor": "Кузнецова Е.Ю.",
                "room": "Д",
                "link": "-"
            }
        ],
        [
            {
                "subject": "Физика",
                "sub_type": "пр",
                "professor": "Логачев И.И.",
                "room": "Д",
                "link": "-"
            },
            {
                "subject": "Физика",
                "sub_type": "лаб",
                "professor": "-",
                "room": "Д",
                "link": "-"
            }
        ]
    ],
    "Friday": [
        [
            {
                "subject": "Физика",
                "sub_type": "лк",
                "professor": "Коробкин Ю.В.",
                "room": "Д",
                "link": "https://events.webinar.ru/21586908/4633176"
            },
            {
                "subject": "ОО программирование",
                "sub_type": "лк",
                "professor": "Путуридзе З.Ш.",
                "room": "Д",
                "link": "-"
            }
        ],
        [
            {
                "subject": "Физ.культура и спорт",
                "sub_type": "-",
                "professor": "-",
                "room": "Д",
                "link": "-"
            },
            {
                "subject": "Физ.культура и спорт",
                "sub_type": "-",
                "professor": "-",
                "room": "Д",
                "link": "-"
            }
        ],
        [
            {
                "subject": "ОО программирование",
                "sub_type": "пр",
                "professor": "Игнатьев Ф.А.",
                "room": "Д",
                "link": "Автоматизированная система обучения \"Аврора\""
            },
            {
                "subject": "ОО программирование",
                "sub_type": "пр",
                "professor": "Игнатьев Ф.А.",
                "room": "Д",
                "link": "-"
            }
        ],
        [
            {
                "subject": "ОО программирование",
                "sub_type": "пр",
                "professor": "Игнатьев Ф.А.",
                "room": "Д",
                "link": "Автоматизированная система обучения \"Аврора\""
            },
            {
                "subject": "ОО программирование",
                "sub_type": "пр",
                "professor": "Игнатьев Ф.А.",
                "room": "Д",
                "link": "-"
            }
        ],
        [
            {
                "subject": "Ин. язык (фр.)",
                "sub_type": "пр",
                "professor": "Иванова Е.А.",
                "room": "Д",
                "link": "https://us04web.zoom.us/j/78807561465?pwd=V2ZESnhtemxiaFBuUzVVbU0yNXpzQT09"
            },
            {
                "subject": "Ин. язык (фр.)",
                "sub_type": "пр",
                "professor": "Иванова Е.А.",
                "room": "Д",
                "link": "-"
            }
        ],
        [
            {
                "subject": "-",
                "sub_type": "-",
                "professor": "-",
                "room": "-",
                "link": "-"
            },
            {
                "subject": "-",
                "sub_type": "-",
                "professor": "-",
                "room": "-",
                "link": "-"
            }
        ]
    ],
    "Saturday": [
        [
            {
                "subject": "Лин. алгебра и АГ",
                "sub_type": "лк",
                "professor": "Берков Н.А.",
                "room": "Д",
                "link": "-"
            },
            {
                "subject": "-",
                "sub_type": "-",
                "professor": "-",
                "room": "-",
                "link": "-"
            }
        ],
        [
            {
                "subject": "Мат. анализ",
                "sub_type": "лк",
                "professor": "Игонина Т.Р.",
                "room": "Д",
                "link": "-"
            },
            {
                "subject": "Физика",
                "sub_type": "лк",
                "professor": "Коробкин Ю.В.",
                "room": "Д",
                "link": "-"
            }
        ],
        [
            {
                "subject": "Лин. алгебра и АГ",
                "sub_type": "пр",
                "professor": "Кузнецова Е.Ю.",
                "room": "Д",
                "link": "-"
            },
            {
                "subject": "Мат. логика и ТА",
                "sub_type": "пр",
                "professor": "пм",
                "room": "Д",
                "link": "-"
            }
        ],
        [
            {
                "subject": "Мат. логика и ТА",
                "sub_type": "лк",
                "professor": "Воронцов А.А.",
                "room": "Д",
                "link": "-"
            },
            {
                "subject": "Мат. логика и ТА",
                "sub_type": "лк",
                "professor": "Воронцов А.А.",
                "room": "Д",
                "link": "-"
            }
        ],
        [
            {
                "subject": "-",
                "sub_type": "-",
                "professor": "-",
                "room": "-",
                "link": "-"
            },
            {
                "subject": "-",
                "sub_type": "-",
                "professor": "-",
                "room": "-",
                "link": "-"
            }
        ],
        [
            {
                "subject": "-",
                "sub_type": "-",
                "professor": "-",
                "room": "-",
                "link": "-"
            },
            {
                "subject": "-",
                "sub_type": "-",
                "professor": "-",
                "room": "-",
                "link": "-"
            }
        ]
    ]
}